deepgpu/__init__.py
deepgpu-0.0.0.dist-info/METADATA
deepgpu-0.0.0.dist-info/WHEEL
deepgpu-0.0.0.dist-info/top_level.txt
deepgpu-0.0.0.dist-info/RECORD
