Metadata-Version: 2.1
Name: deepgpu
Version: 0.0.0
Summary: deepgpu
Home-page: https://www.aliyun.com
